align_benchmark/__init__.py
align_benchmark/__main__.py
align_benchmark/align_benchmark.py
align_benchmark/benchmark.py
align_benchmark/twotuple_metric.py
LICENSE
align_benchmark-0.1.1.dist-info/entry_points.txt
align_benchmark-0.1.1.dist-info/LICENSE
align_benchmark-0.1.1.dist-info/WHEEL
align_benchmark-0.1.1.dist-info/METADATA
align_benchmark-0.1.1.dist-info/RECORD
