Metadata-Version: 2.1
Name: align-benchmark
Version: 0.1.1
Summary: Benchmark tests for dualtext alignment
Home-page: https://github.com/ffreemt/text-alignment-benchmarks
License: MIT
Author: ffreemt
Requires-Python: >=3.8,<4.0
Classifier: License :: OSI Approved :: MIT License
Classifier: Programming Language :: Python :: 3
Classifier: Programming Language :: Python :: 3.10
Classifier: Programming Language :: Python :: 3.8
Classifier: Programming Language :: Python :: 3.9
Requires-Dist: icecream (>=2.1.1,<3.0.0)
Requires-Dist: logzero (>=1.7.0,<2.0.0)
Requires-Dist: numpy (>=1.22.1,<2.0.0)
Requires-Dist: openpyxl (>=3.0.9,<4.0.0)
Requires-Dist: pandas (>=1.4.0,<2.0.0)
Project-URL: Repository, https://github.com/ffreemt/text-alignment-benchmarks
